mongodb_connect/__init__.py
mongodb_connect/mongo_crud.py
Python_mongoDB_Connect1-0.0.4.dist-info/LICENSE
Python_mongoDB_Connect1-0.0.4.dist-info/METADATA
Python_mongoDB_Connect1-0.0.4.dist-info/WHEEL
Python_mongoDB_Connect1-0.0.4.dist-info/top_level.txt
Python_mongoDB_Connect1-0.0.4.dist-info/RECORD
